storage/__init__.py
storage/backends/__init__.py
storage/backends/qiniu_storage.py
storage/backends/utils.py
django_qns-0.0.1.dist-info/LICENSE
django_qns-0.0.1.dist-info/METADATA
django_qns-0.0.1.dist-info/WHEEL
django_qns-0.0.1.dist-info/top_level.txt
django_qns-0.0.1.dist-info/RECORD
