Metadata-Version: 2.1
Name: django-qns
Version: 0.0.1
Summary: add qiniuyun storage support for Django
Home-page: https://github.com/YuanBLQ/django-qns
Author: Yuan
Author-email: 
License: MIT License
Keywords: django,qiniu,qiniuyun,qiniucloud,storage
Platform: UNKNOWN
Classifier: Programming Language :: Python :: 3
Classifier: License :: OSI Approved :: MIT License
Classifier: Operating System :: OS Independent
Requires-Dist: request (>=2.5.0)
Requires-Dist: qiniu (>=7.2.6)
